<?xml version="1.0" encoding="utf-8"?><soap:Envelope xmlns:soap="http://www.w3.org/2003/05/soap-envelope" xmlns:xsi="http://www.w3.org/2001/XMLSchema-instance" xmlns:xsd="http://www.w3.org/2001/XMLSchema"><soap:Body><GetDepartureBoardResponse xmlns="http://thalesgroup.com/RTTI/2016-02-16/ldb/"><GetStationBoardResult xmlns:lt="http://thalesgroup.com/RTTI/2012-01-13/ldb/types" xmlns:lt8="http://thalesgroup.com/RTTI/2021-11-01/ldb/types" xmlns:lt6="http://thalesgroup.com/RTTI/2017-02-02/ldb/types" xmlns:lt7="http://thalesgroup.com/RTTI/2017-10-01/ldb/types" xmlns:lt4="http://thalesgroup.com/RTTI/2015-11-27/ldb/types" xmlns:lt5="http://thalesgroup.com/RTTI/2016-02-16/ldb/types" xmlns:lt2="http://thalesgroup.com/RTTI/2014-02-20/ldb/types" xmlns:lt3="http://thalesgroup.com/RTTI/2015-05-14/ldb/types"><lt4:generatedAt>2025-10-20T20:22:17.7097715+01:00</lt4:generatedAt><lt4:locationName>Herne Hill</lt4:locationName><lt4:crs>HNH</lt4:crs><lt4:platformAvailable>true</lt4:platformAvailable><lt5:trainServices><lt5:service><lt4:std>20:22</lt4:std><lt4:etd>20:29</lt4:etd><lt4:platform>3</lt4:platform><lt4:operator>Southeastern</lt4:operator><lt4:operatorCode>SE</lt4:operatorCode><lt4:serviceType>train</lt4:serviceType><lt4:length>8</lt4:length><lt4:delayReason>This service has been delayed by a fault on a train earlier</lt4:delayReason><lt4:serviceID>1771218HERNEH__</lt4:serviceID><lt5:origin><lt4:location><lt4:locationName>London Victoria</lt4:locationName><lt4:crs>VIC</lt4:crs></lt4:location></lt5:origin><lt5:destination><lt4:location><lt4:locationName>Orpington</lt4:locationName><lt4:crs>ORP</lt4:crs></lt4:location></lt5:destination></lt5:service><lt5:service><lt4:std>20:23</lt4:std><lt4:etd>20:36</lt4:etd><lt4:platform>2</lt4:platform><lt4:operator>Southeastern</lt4:operator><lt4:operatorCode>SE</lt4:operatorCode><lt4:serviceType>train</lt4:serviceType><lt4:length>8</lt4:length><lt4:delayReason>This service has been delayed by a broken down train earlier today</lt4:delayReason><lt4:serviceID>1771606HERNEH__</lt4:serviceID><lt5:origin><lt4:location><lt4:locationName>Orpington</lt4:locationName><lt4:crs>ORP</lt4:crs></lt4:location></lt5:origin><lt5:destination><lt4:location><lt4:locationName>London Victoria</lt4:locationName><lt4:crs>VIC</lt4:crs></lt4:location></lt5:destination></lt5:service><lt5:service><lt4:std>20:27</lt4:std><lt4:etd>On time</lt4:etd><lt4:platform>1</lt4:platform><lt4:operator>Thameslink</lt4:operator><lt4:operatorCode>TL</lt4:operatorCode><lt4:serviceType>train</lt4:serviceType><lt4:length>8</lt4:length><lt4:serviceID>1762873HERNEH__</lt4:serviceID><lt5:origin><lt4:location><lt4:locationName>Sutton (London)</lt4:locationName><lt4:crs>SUO</lt4:crs></lt4:location></lt5:origin><lt5:destination><lt4:location><lt4:locationName>St Albans</lt4:locationName><lt4:crs>SAC</lt4:crs></lt4:location></lt5:destination></lt5:service><lt5:service><lt4:std>20:35</lt4:std><lt4:etd>On time</lt4:etd><lt4:platform>4</lt4:platform><lt4:operator>Thameslink</lt4:operator><lt4:operatorCode>TL</lt4:operatorCode><lt4:serviceType>train</lt4:serviceType><lt4:length>8</lt4:length><lt4:serviceID>1763747HERNEH__</lt4:serviceID><lt5:origin><lt4:location><lt4:locationName>St Albans</lt4:locationName><lt4:crs>SAC</lt4:crs></lt4:location></lt5:origin><lt5:destination><lt4:location><lt4:locationName>Sutton (London)</lt4:locationName><lt4:crs>SUO</lt4:crs><lt4:via>via Wimbledon</lt4:via></lt4:location></lt5:destination></lt5:service><lt5:service><lt4:std>20:37</lt4:std><lt4:etd>Cancelled</lt4:etd><lt4:operator>Southeastern</lt4:operator><lt4:operatorCode>SE</lt4:operatorCode><lt4:isCancelled>true</lt4:isCancelled><lt4:serviceType>train</lt4:serviceType><lt4:cancelReason>This service has been cancelled because of a fault on this train</lt4:cancelReason><lt4:serviceID>1771213HERNEH__</lt4:serviceID><lt5:origin><lt4:location><lt4:locationName>London Victoria</lt4:locationName><lt4:crs>VIC</lt4:crs></lt4:location></lt5:origin><lt5:destination><lt4:location><lt4:locationName>Orpington</lt4:locationName><lt4:crs>ORP</lt4:crs></lt4:location></lt5:destination></lt5:service><lt5:service><lt4:std>20:38</lt4:std><lt4:etd>20:48</lt4:etd><lt4:platform>2</lt4:platform><lt4:operator>Southeastern</lt4:operator><lt4:operatorCode>SE</lt4:operatorCode><lt4:serviceType>train</lt4:serviceType><lt4:length>8</lt4:length><lt4:delayReason>This service has been delayed by a broken down train earlier today</lt4:delayReason><lt4:serviceID>1771603HERNEH__</lt4:serviceID><lt5:origin><lt4:location><lt4:locationName>Orpington</lt4:locationName><lt4:crs>ORP</lt4:crs></lt4:location></lt5:origin><lt5:destination><lt4:location><lt4:locationName>London Victoria</lt4:locationName><lt4:crs>VIC</lt4:crs></lt4:location></lt5:destination></lt5:service><lt5:service><lt4:std>20:42</lt4:std><lt4:etd>On time</lt4:etd><lt4:platform>1</lt4:platform><lt4:operator>Thameslink</lt4:operator><lt4:operatorCode>TL</lt4:operatorCode><lt4:serviceType>train</lt4:serviceType><lt4:length>8</lt4:length><lt4:serviceID>1763740HERNEH__</lt4:serviceID><lt5:origin><lt4:location><lt4:locationName>Sutton (London)</lt4:locationName><lt4:crs>SUO</lt4:crs></lt4:location></lt5:origin><lt5:destination><lt4:location><lt4:locationName>St Albans</lt4:locationName><lt4:crs>SAC</lt4:crs></lt4:location></lt5:destination></lt5:service><lt5:service><lt4:std>20:50</lt4:std><lt4:etd>On time</lt4:etd><lt4:platform>4</lt4:platform><lt4:operator>Thameslink</lt4:operator><lt4:operatorCode>TL</lt4:operatorCode><lt4:serviceType>train</lt4:serviceType><lt4:length>8</lt4:length><lt4:serviceID>1762885HERNEH__</lt4:serviceID><lt5:origin><lt4:location><lt4:locationName>St Albans</lt4:locationName><lt4:crs>SAC</lt4:crs></lt4:location></lt5:origin><lt5:destination><lt4:location><lt4:locationName>Sutton (London)</lt4:locationName><lt4:crs>SUO</lt4:crs></lt4:location></lt5:destination></lt5:service><lt5:service><lt4:std>20:52</lt4:std><lt4:etd>20:58</lt4:etd><lt4:platform>3</lt4:platform><lt4:operator>Southeastern</lt4:operator><lt4:operatorCode>SE</lt4:operatorCode><lt4:serviceType>train</lt4:serviceType><lt4:length>8</lt4:length><lt4:delayReason>This service has been delayed by a broken down train earlier today</lt4:delayReason><lt4:serviceID>1771209HERNEH__</lt4:serviceID><lt5:origin><lt4:location><lt4:locationName>London Victoria</lt4:locationName><lt4:crs>VIC</lt4:crs></lt4:location></lt5:origin><lt5:destination><lt4:location><lt4:locationName>Orpington</lt4:locationName><lt4:crs>ORP</lt4:crs></lt4:location></lt5:destination></lt5:service><lt5:service><lt4:std>20:53</lt4:std><lt4:etd>On time</lt4:etd><lt4:platform>2</lt4:platform><lt4:operator>Southeastern</lt4:operator><lt4:operatorCode>SE</lt4:operatorCode><lt4:serviceType>train</lt4:serviceType><lt4:length>8</lt4:length><lt4:serviceID>1771596HERNEH__</lt4:serviceID><lt5:origin><lt4:location><lt4:locationName>Orpington</lt4:locationName><lt4:crs>ORP</lt4:crs></lt4:location></lt5:origin><lt5:destination><lt4:location><lt4:locationName>London Victoria</lt4:locationName><lt4:crs>VIC</lt4:crs></lt4:location></lt5:destination></lt5:service><lt5:service><lt4:std>20:57</lt4:std><lt4:etd>On time</lt4:etd><lt4:platform>1</lt4:platform><lt4:operator>Thameslink</lt4:operator><lt4:operatorCode>TL</lt4:operatorCode><lt4:serviceType>train</lt4:serviceType><lt4:length>8</lt4:length><lt4:serviceID>1762879HERNEH__</lt4:serviceID><lt5:origin><lt4:location><lt4:locationName>Sutton (London)</lt4:locationName><lt4:crs>SUO</lt4:crs></lt4:location></lt5:origin><lt5:destination><lt4:location><lt4:locationName>St Albans</lt4:locationName><lt4:crs>SAC</lt4:crs></lt4:location></lt5:destination></lt5:service><lt5:service><lt4:std>21:05</lt4:std><lt4:etd>On time</lt4:etd><lt4:operator>Thameslink</lt4:operator><lt4:operatorCode>TL</lt4:operatorCode><lt4:serviceType>train</lt4:serviceType><lt4:length>8</lt4:length><lt4:serviceID>1763751HERNEH__</lt4:serviceID><lt5:origin><lt4:location><lt4:locationName>St Albans</lt4:locationName><lt4:crs>SAC</lt4:crs></lt4:location></lt5:origin><lt5:destination><lt4:location><lt4:locationName>Sutton (London)</lt4:locationName><lt4:crs>SUO</lt4:crs><lt4:via>via Wimbledon</lt4:via></lt4:location></lt5:destination></lt5:service><lt5:service><lt4:std>21:07</lt4:std><lt4:etd>21:10</lt4:etd><lt4:operator>Southeastern</lt4:operator><lt4:operatorCode>SE</lt4:operatorCode><lt4:serviceType>train</lt4:serviceType><lt4:length>8</lt4:length><lt4:serviceID>1771203HERNEH__</lt4:serviceID><lt5:origin><lt4:location><lt4:locationName>London Victoria</lt4:locationName><lt4:crs>VIC</lt4:crs></lt4:location></lt5:origin><lt5:destination><lt4:location><lt4:locationName>Orpington</lt4:locationName><lt4:crs>ORP</lt4:crs></lt4:location></lt5:destination></lt5:service><lt5:service><lt4:std>21:08</lt4:std><lt4:etd>On time</lt4:etd><lt4:operator>Southeastern</lt4:operator><lt4:operatorCode>SE</lt4:operatorCode><lt4:serviceType>train</lt4:serviceType><lt4:length>8</lt4:length><lt4:serviceID>1771590HERNEH__</lt4:serviceID><lt5:origin><lt4:location><lt4:locationName>Orpington</lt4:locationName><lt4:crs>ORP</lt4:crs></lt4:location></lt5:origin><lt5:destination><lt4:location><lt4:locationName>London Victoria</lt4:locationName><lt4:crs>VIC</lt4:crs></lt4:location></lt5:destination></lt5:service><lt5:service><lt4:std>21:12</lt4:std><lt4:etd>On time</lt4:etd><lt4:operator>Thameslink</lt4:operator><lt4:operatorCode>TL</lt4:operatorCode><lt4:serviceType>train</lt4:serviceType><lt4:length>8</lt4:length><lt4:serviceID>1763745HERNEH__</lt4:serviceID><lt5:origin><lt4:location><lt4:locationName>Sutton (London)</lt4:locationName><lt4:crs>SUO</lt4:crs></lt4:location></lt5:origin><lt5:destination><lt4:location><lt4:locationName>St Albans</lt4:locationName><lt4:crs>SAC</lt4:crs></lt4:location></lt5:destination></lt5:service><lt5:service><lt4:std>21:20</lt4:std><lt4:etd>On time</lt4:etd><lt4:operator>Thameslink</lt4:operator><lt4:operatorCode>TL</lt4:operatorCode><lt4:serviceType>train</lt4:serviceType><lt4:length>8</lt4:length><lt4:serviceID>1762887HERNEH__</lt4:serviceID><lt5:origin><lt4:location><lt4:locationName>St Albans</lt4:locationName><lt4:crs>SAC</lt4:crs></lt4:location></lt5:origin><lt5:destination><lt4:location><lt4:locationName>Sutton (London)</lt4:locationName><lt4:crs>SUO</lt4:crs></lt4:location></lt5:destination></lt5:service></lt5:trainServices></GetStationBoardResult></GetDepartureBoardResponse></soap:Body></soap:Envelope>